tap_spreadsheets/__init__.py
tap_spreadsheets/__main__.py
tap_spreadsheets/storage.py
tap_spreadsheets/stream.py
tap_spreadsheets/tap.py
tap_spreadsheets-1.1.2.dist-info/METADATA
tap_spreadsheets-1.1.2.dist-info/WHEEL
tap_spreadsheets-1.1.2.dist-info/entry_points.txt
tap_spreadsheets-1.1.2.dist-info/licenses/LICENSE
tap_spreadsheets-1.1.2.dist-info/RECORD
