Metadata-Version: 2.4
Name: tap-spreadsheets
Version: 1.1.2
Summary: Singer tap for spreadsheets, built with the Meltano Singer SDK.
Author-email: Luca Capra <luca.capra@spindox.it>
License-Expression: Apache-2.0
License-File: LICENSE
Keywords: ELT,Spreadsheets
Classifier: Intended Audience :: Developers
Classifier: License :: OSI Approved :: Apache Software License
Classifier: Operating System :: OS Independent
Classifier: Programming Language :: Python :: 3.10
Classifier: Programming Language :: Python :: 3.11
Classifier: Programming Language :: Python :: 3.12
Classifier: Programming Language :: Python :: 3.13
Classifier: Programming Language :: Python :: 3.14
Requires-Python: >=3.10
Requires-Dist: openpyxl>=3.1.5
Requires-Dist: python-dateutil>=2.9.0.post0
Requires-Dist: s3fs>=2025.9.0
Requires-Dist: singer-sdk[faker]<0.53.0,>=0.49.1
Provides-Extra: s3
Requires-Dist: s3fs~=2025.9.0; extra == 's3'
